AUTHORS
CHANGELOG.txt
DESCRIPTION
LICENSE
MANIFEST.in
README.rst
setup.cfg
setup.py
cmsplugin_frequently/__init__.py
cmsplugin_frequently/cms_plugins.py
cmsplugin_frequently/models.py
cmsplugin_frequently.egg-info/PKG-INFO
cmsplugin_frequently.egg-info/SOURCES.txt
cmsplugin_frequently.egg-info/dependency_links.txt
cmsplugin_frequently.egg-info/requires.txt
cmsplugin_frequently.egg-info/top_level.txt
cmsplugin_frequently/management/__init__.py
cmsplugin_frequently/management/commands/__init__.py
cmsplugin_frequently/management/commands/migrate_to_frequently_v1.py
cmsplugin_frequently/migrations/0001_initial.py
cmsplugin_frequently/migrations/__init__.py
cmsplugin_frequently/south_migrations/0001_initial.py
cmsplugin_frequently/south_migrations/__init__.py
cmsplugin_frequently/tests/__init__.py
cmsplugin_frequently/tests/cms_plugins_tests.py
cmsplugin_frequently/tests/settings.py
cmsplugin_frequently/tests/test_settings.py
cmsplugin_frequently/tests/urls.py
cmsplugin_frequently/tests/test_app/__init__.py
cmsplugin_frequently/tests/test_app/models.py
cmsplugin_frequently/tests/test_app/templates/400.html
cmsplugin_frequently/tests/test_app/templates/404.html
cmsplugin_frequently/tests/test_app/templates/500.html
cmsplugin_frequently/tests/test_app/templates/base.html
cmsplugin_frequently/tests/test_app/templates/cms.html
cmsplugin_frequently/tests/test_app/templates/tag_test.html