Metadata-Version: 1.0
Name: cmsplugin-frequently
Version: 0.2
Summary: django-cms plugin and apphook for the django-frequently app.
